Metadata-Version: 2.1
Name: uuvmissionsim
Version: 0.1.1
Summary: A UUV ocean data collection mission simulator based on an ocean model (ROMS)
Home-page: https://github.com/Prakarsha01/UUVMissionSim
Author: Ratna Prakarsha Kandukuri
Author-email: rpkandukuri@outlook.com
Requires-Python: >=3.6
Requires-Dist: xarray
Requires-Dist: numpy
Requires-Dist: pandas
Requires-Dist: joblib
Requires-Dist: xroms
Requires-Dist: matplotlib
